{ "a____": { "aa___": { "aaa__": [ "aaaaa", "aaaba", "aaaca", "aaada", "aaaea",
                                   "aaafa", "aaaga", "aaaha", "aaaia", "aaaja",
                                   "aaaka" ],
                        "aab__": [ "aabaa", "aabba", "aabca", "aabda", "aabea",
                                   "aabfa", "aabga", "aabha", "aabia", "aabja",
                                   "aabka" ],
                        "aac__": [ "aacaa", "aacba", "aacca", "aacda", "aacea",
                                   "aacfa", "aacga", "aacha", "aacia", "aacja",
                                   "aacka" ] },
             "ab___": { "aba__": [ "abaaa", "ababa", "abaca", "abada", "abaea",
                                   "abafa", "abaga", "abaha", "abaia", "abaja",
                                   "abaka" ],
                        "abb__": [ "abbaa", "abbba", "abbca", "abbda", "abbea",
                                   "abbfa", "abbga", "abbha", "abbia", "abbja",
                                   "abbka" ],
                        "abc__": [ "abcaa", "abcba", "abcca", "abcda", "abcea",
                                   "abcfa", "abcga", "abcha", "abcia", "abcja",
                                   "abcka" ] },
             "ac___": { "aca__": [ "acaaa", "acaba", "acaca", "acada", "acaea",
                                   "acafa", "acaga", "acaha", "acaia", "acaja",
                                   "acaka" ],
                        "acb__": [ "acbaa", "acbba", "acbca", "acbda", "acbea",
                                   "acbfa", "acbga", "acbha", "acbia", "acbja",
                                   "acbka" ],
                        "acc__": [ "accaa", "accba", "accca", "accda", "accea",
                                   "accfa", "accga", "accha", "accia", "accja",
                                   "accka" ] } },
  "b____": { "ba___": { "baa__": [ "baaaa", "baaba", "baaca", "baada", "baaea",
                                   "baafa", "baaga", "baaha", "baaia", "baaja",
                                   "baaka" ],
                        "bab__": [ "babaa", "babba", "babca", "babda", "babea",
                                   "babfa", "babga", "babha", "babia", "babja",
                                   "babka" ],
                        "bac__": [ "bacaa", "bacba", "bacca", "bacda", "bacea",
                                   "bacfa", "bacga", "bacha", "bacia", "bacja",
                                   "backa" ] },
             "bb___": { "bba__": [ "bbaaa", "bbaba", "bbaca", "bbada", "bbaea",
                                   "bbafa", "bbaga", "bbaha", "bbaia", "bbaja",
                                   "bbaka" ],
                        "bbb__": [ "bbbaa", "bbbba", "bbbca", "bbbda", "bbbea",
                                   "bbbfa", "bbbga", "bbbha", "bbbia", "bbbja",
                                   "bbbka" ],
                        "bbc__": [ "bbcaa", "bbcba", "bbcca", "bbcda", "bbcea",
                                   "bbcfa", "bbcga", "bbcha", "bbcia", "bbcja",
                                   "bbcka" ] },
             "bc___": { "bca__": [ "bcaaa", "bcaba", "bcaca", "bcada", "bcaea",
                                   "bcafa", "bcaga", "bcaha", "bcaia", "bcaja",
                                   "bcaka" ],
                        "bcb__": [ "bcbaa", "bcbba", "bcbca", "bcbda", "bcbea",
                                   "bcbfa", "bcbga", "bcbha", "bcbia", "bcbja",
                                   "bcbka" ],
                        "bcc__": [ "bccaa", "bccba", "bccca", "bccda", "bccea",
                                   "bccfa", "bccga", "bccha", "bccia", "bccja",
                                   "bccka" ] } },
  "c____": { "ca___": { "caa__": [ "caaaa", "caaba", "caaca", "caada", "caaea",
                                   "caafa", "caaga", "caaha", "caaia", "caaja",
                                   "caaka" ],
                        "cab__": [ "cabaa", "cabba", "cabca", "cabda", "cabea",
                                   "cabfa", "cabga", "cabha", "cabia", "cabja",
                                   "cabka" ],
                        "cac__": [ "cacaa", "cacba", "cacca", "cacda", "cacea",
                                   "cacfa", "cacga", "cacha", "cacia", "cacja",
                                   "cacka" ] },
             "cb___": { "cba__": [ "cbaaa", "cbaba", "cbaca", "cbada", "cbaea",
                                   "cbafa", "cbaga", "cbaha", "cbaia", "cbaja",
                                   "cbaka" ],
                        "cbb__": [ "cbbaa", "cbbba", "cbbca", "cbbda", "cbbea",
                                   "cbbfa", "cbbga", "cbbha", "cbbia", "cbbja",
                                   "cbbka" ],
                        "cbc__": [ "cbcaa", "cbcba", "cbcca", "cbcda", "cbcea",
                                   "cbcfa", "cbcga", "cbcha", "cbcia", "cbcja",
                                   "cbcka" ] },
             "cc___": { "cca__": [ "ccaaa", "ccaba", "ccaca", "ccada", "ccaea",
                                   "ccafa", "ccaga", "ccaha", "ccaia", "ccaja",
                                   "ccaka" ],
                        "ccb__": [ "ccbaa", "ccbba", "ccbca", "ccbda", "ccbea",
                                   "ccbfa", "ccbga", "ccbha", "ccbia", "ccbja",
                                   "ccbka" ],
                        "ccc__": [ "cccaa", "cccba", "cccca", "cccda", "cccea",
                                   "cccfa", "cccga", "cccha", "cccia", "cccja",
                                   "cccka" ] } } }
